setup.py
safygiphy/__init__.py
safygiphy.egg-info/PKG-INFO
safygiphy.egg-info/SOURCES.txt
safygiphy.egg-info/dependency_links.txt
safygiphy.egg-info/requires.txt
safygiphy.egg-info/top_level.txt