Metadata-Version: 1.0
Name: safygiphy
Version: 1.0.5
Summary: API Wrapper for the online Gif library, Giphy
Home-page: https://code.tetraetc.com
Author: TetraEtc
Author-email: administrator@tetraetc.com
License: UNKNOWN
Platform: UNKNOWN
